[
 {
  "table":"DDDDLSRC",
  "data":
  [
   {
    "DDLNAME":"ZARETE_DBS_DD_T001",
    "AS4LOCAL":"N",
    "AS4USER":"SAP_CUSTOMER",
    "AS4DATE":"0000-00-00",
    "AS4TIME":"00:00:00",
    "SOURCE":"@AccessControl.authorizationCheck: #NOT_REQUIRED\r\n@EndUserText.label: 'Log Bilgileri'\r\n\r\ndefine root view entity ZARETE_DBS_DD_T001\r\n  as select from zarete_dbs_t001\r\n{\r\n  key log_id                as LogId,\r\n      sapinvoiceid          as Sapinvoiceid,\r\n      msgid                 as Msgid,\r\n      msgno                 as Msgno,\r\n      msgty                 as Msgty,\r\n      msgv1                 as Msgv1,\r\n      msgv2                 as Msgv2,\r\n      msgv3                 as Msgv3,\r\n      msgv4                 as Msgv4,\r\n      message               as Message,\r\n      @Semantics.user.createdBy: true\r\n      created_by            as CreatedBy,\r\n      @Semantics.systemDateTime.createdAt: true\r\n      created_at            as CreatedAt,\r\n      @Semantics.systemDateTime.lastChangedAt: true\r\n      last_changed_at       as LastChangedAt,\r\n      @Semantics.user.localInstanceLastChangedBy: true\r\n      local_last_changed_by as LocalLastChangedBy,\r\n      @Semantics.systemDateTime.localInstanceLastChangedAt: true\r\n      local_last_changed_at as LocalLastChangedAt\r\n}\r\n/*+[internal] {\n\"BASEINFO\":\n{\n\"FROM\":\n[\n\"ZARETE_DBS_T001\"\n],\n\"ASSOCIATED\":\n[],\n\"BASE\":\n[],\n\"ANNO_REF\":\n[],\n\"SCALAR_FUNCTION\":\n[],\n\"VERSION\":0,\n\"ANNOREF_EVALUATION_ERROR\":\"\"\n}\n}*/",
    "PARENTNAME":"",
    "ACTFLAG":"",
    "CHGFLAG":"",
    "SOURCE_TYPE":"W",
    "SOURCE_ORIGIN":"0",
    "ABAP_LANGUAGE_VERSION":"5"
   }
  ]
 },
 {
  "table":"DDDDLSRC02BT",
  "data":
  [
   {
    "DDLNAME":"ZARETE_DBS_DD_T001",
    "STRUCOBJN":"ZARETE_DBS_DD_T001",
    "DDLANGUAGE":"E",
    "AS4LOCAL":"N",
    "DDTEXT":"Log Bilgileri"
   }
  ]
 },
 {
  "table":"DDDDLSRCT",
  "data":
  [
   {
    "DDLNAME":"ZARETE_DBS_DD_T001",
    "DDLANGUAGE":"E",
    "AS4LOCAL":"N",
    "DDTEXT":"Log Bilgileri"
   }
  ]
 },
 {
  "table":"DDFIELDANNO",
  "data":
  [
   {
    "STRUCOBJN":"ZARETE_DBS_DD_T001",
    "LFIELDNAME":"CREATEDAT",
    "NAME":"SEMANTICS",
    "POSITION":5,
    "VALUE":""
   },
   {
    "STRUCOBJN":"ZARETE_DBS_DD_T001",
    "LFIELDNAME":"CREATEDAT",
    "NAME":"SEMANTICS.SYSTEMDATETIME.CREATEDAT",
    "POSITION":6,
    "VALUE":"true"
   },
   {
    "STRUCOBJN":"ZARETE_DBS_DD_T001",
    "LFIELDNAME":"CREATEDBY",
    "NAME":"SEMANTICS",
    "POSITION":3,
    "VALUE":""
   },
   {
    "STRUCOBJN":"ZARETE_DBS_DD_T001",
    "LFIELDNAME":"CREATEDBY",
    "NAME":"SEMANTICS.USER.CREATEDBY",
    "POSITION":4,
    "VALUE":"true"
   },
   {
    "STRUCOBJN":"ZARETE_DBS_DD_T001",
    "LFIELDNAME":"LASTCHANGEDAT",
    "NAME":"SEMANTICS",
    "POSITION":7,
    "VALUE":""
   },
   {
    "STRUCOBJN":"ZARETE_DBS_DD_T001",
    "LFIELDNAME":"LASTCHANGEDAT",
    "NAME":"SEMANTICS.SYSTEMDATETIME.LASTCHANGEDAT",
    "POSITION":8,
    "VALUE":"true"
   },
   {
    "STRUCOBJN":"ZARETE_DBS_DD_T001",
    "LFIELDNAME":"LOCALLASTCHANGEDAT",
    "NAME":"SEMANTICS",
    "POSITION":11,
    "VALUE":""
   },
   {
    "STRUCOBJN":"ZARETE_DBS_DD_T001",
    "LFIELDNAME":"LOCALLASTCHANGEDAT",
    "NAME":"SEMANTICS.SYSTEMDATETIME.LOCALINSTANCELASTCHANGEDAT",
    "POSITION":12,
    "VALUE":"true"
   },
   {
    "STRUCOBJN":"ZARETE_DBS_DD_T001",
    "LFIELDNAME":"LOCALLASTCHANGEDBY",
    "NAME":"SEMANTICS",
    "POSITION":9,
    "VALUE":""
   },
   {
    "STRUCOBJN":"ZARETE_DBS_DD_T001",
    "LFIELDNAME":"LOCALLASTCHANGEDBY",
    "NAME":"SEMANTICS.USER.LOCALINSTANCELASTCHANGEDBY",
    "POSITION":10,
    "VALUE":"true"
   },
   {
    "STRUCOBJN":"ZARETE_DBS_DD_T001",
    "LFIELDNAME":"MANDT",
    "NAME":"ABAPCATALOG",
    "POSITION":1,
    "VALUE":""
   },
   {
    "STRUCOBJN":"ZARETE_DBS_DD_T001",
    "LFIELDNAME":"MANDT",
    "NAME":"ABAPCATALOG.INTERNAL.ISMANDT",
    "POSITION":2,
    "VALUE":""
   }
  ]
 },
 {
  "table":"DDHEADANNO",
  "data":
  [
   {
    "STRUCOBJN":"ZARETE_DBS_DD_T001",
    "NAME":"ACCESSCONTROL",
    "POSITION":1,
    "VALUE":""
   },
   {
    "STRUCOBJN":"ZARETE_DBS_DD_T001",
    "NAME":"ACCESSCONTROL.AUTHORIZATIONCHECK",
    "POSITION":2,
    "VALUE":"#NOT_REQUIRED"
   },
   {
    "STRUCOBJN":"ZARETE_DBS_DD_T001",
    "NAME":"ENDUSERTEXT",
    "POSITION":3,
    "VALUE":""
   },
   {
    "STRUCOBJN":"ZARETE_DBS_DD_T001",
    "NAME":"ENDUSERTEXT.LABEL",
    "POSITION":4,
    "VALUE":"'Log Bilgileri'"
   }
  ]
 },
 {
  "table":"DDLDEPENDENCY",
  "data":
  [
   {
    "DDLNAME":"ZARETE_DBS_DD_T001",
    "OBJECTNAME":"ZARETE_DBS_DD_T001",
    "STATE":"N",
    "OBJECTTYPE":"STOB"
   }
  ]
 },
 {
  "table":"TADIR",
  "data":
  [
   {
    "PGMID":"R3TR",
    "OBJECT":"DDLS",
    "OBJ_NAME":"ZARETE_DBS_DD_T001",
    "KORRNUM":"",
    "SRCSYSTEM":"...",
    "AUTHOR":"SAP_CUSTOMER",
    "SRCDEP":"",
    "DEVCLASS":"ZARETE_DBS_VDM",
    "GENFLAG":"",
    "EDTFLAG":"",
    "CPROJECT":" S",
    "MASTERLANG":"E",
    "VERSID":"",
    "PAKNOCHECK":"",
    "OBJSTABLTY":"",
    "COMPONENT":"ZARETE_DBS",
    "CRELEASE":"100",
    "DELFLAG":"",
    "TRANSLTTXT":"",
    "CREATED_ON":"2025-05-30",
    "CHECK_DATE":"2025-05-30",
    "CHECK_CFG":""
   }
  ]
 }
]